wukongqueue/__init__.py
wukongqueue/_commu_proto.py
wukongqueue/_item_wrapper.py
wukongqueue/client.py
wukongqueue/connection.py
wukongqueue/exceptions.py
wukongqueue/server.py
wukongqueue/utils.py
wukongqueue-0.0.6.dist-info/LICENSE
wukongqueue-0.0.6.dist-info/METADATA
wukongqueue-0.0.6.dist-info/WHEEL
wukongqueue-0.0.6.dist-info/top_level.txt
wukongqueue-0.0.6.dist-info/RECORD
