Metadata-Version: 2.1
Name: wukongqueue
Version: 0.0.6
Summary: A lightweight and convenient cross network FIFO queue service based on TCP protocol.
Home-page: https://github.com/chaseSpace/WukongQueue
Author: chaseSpace
Author-email: randomlilei@gmail.com
License: UNKNOWN
Keywords: cross network queue
Platform: UNKNOWN
Requires-Python: >=3.5
